geneanot/Fasta_segment.py
geneanot/Gene_annotation.py
geneanot/__init__.py
geneanot/annotation_file_utils.py
geneanot/ensembl_gene_annotations_utils.py
geneanot/ensembl_rest_utils.py
geneanot/ensembl_utils.py
geneanot/excel_utils.py
geneanot/genomic_sequences_utils.py
geneanot/py.typed
geneanot/rest_api_utils.py
geneanot/translation.py
geneanot-0.5.1.dist-info/METADATA
geneanot-0.5.1.dist-info/WHEEL
geneanot-0.5.1.dist-info/entry_points.txt
geneanot-0.5.1.dist-info/licenses/LICENSE
geneanot-0.5.1.dist-info/RECORD
