Metadata-Version: 2.4
Name: geneanot
Version: 0.5.1
Summary: Vertebrates gene annotation based on Ensembl.
Project-URL: Homepage, https://github.com/yoramzarai/geneanot
Author-email: yoramzarai <yoram.zarai@gmail.com>
License-File: LICENSE
Classifier: Intended Audience :: Science/Research
Classifier: License :: OSI Approved :: MIT License
Classifier: Operating System :: OS Independent
Classifier: Programming Language :: Python :: 3.10
Classifier: Topic :: Scientific/Engineering :: Bio-Informatics
Requires-Python: >=3.10
Requires-Dist: openpyxl>=3.1.5
Requires-Dist: pandas>=2.2.3
Requires-Dist: requests>=2.32.3
Requires-Dist: xlsxwriter>=3.2.0
